{ "scene" : {"camera" :{ "x":0, "y":0, "coordx":207, "coordy":50, "cx":227, "cy":70, "rotation":0, "altura":170, "zancada":30, "salto":0.5} , "sala" :{"id" : "sala", "nombre" : "Sala1",  "location": "./uploads/IMG/Vicente/sala1.png", "pathX3DSin": "./uploads/X3D/Vicente/scene1.x3d", "pathX3D": "./uploads/X3D/Vicente/expo.x3d", "pathOBJ": "./uploads/OBJ/Vicente/scene1.obj",  "pixAncho": "636",  "pixAlto": "500",  "ancho": "61",  "alto": "46"} , "esculturas" : [{ "nombre" : "Venus0",  "nombreBD": "Venus", "id": "Venus0", "height":40, "width":40, "location": "./uploads/IMG/Vicente/venus.jpg", "x":0, "y":0, "coordx":357, "coordy":95, "cx":377, "cy":115, "rotation":0, "pedestalAncho":0, "pedestalAlto":0, "pathX3D": "./uploads/X3D/Vicente/venus.x3d", "pathOBJ": "./uploads/OBJ/Vicente/venus.obj"} , { "nombre" : "El Pensador1",  "nombreBD": "El Pensador", "id": "El Pensador1", "height":40, "width":40, "location": "./uploads/IMG/Vicente/thinkerCenital.jpg", "x":0, "y":0, "coordx":392.7080078125, "coordy":184.8800048828125, "cx":412.7080078125, "cy":204.8800048828125, "rotation":180, "pedestalAncho":0, "pedestalAlto":0, "pathX3D": "./uploads/X3D/Vicente/thinker.x3d", "pathOBJ": "./uploads/OBJ/Vicente/thinker.obj"} , { "nombre" : "Venus2",  "nombreBD": "Venus", "id": "Venus2", "height":40, "width":40, "location": "./uploads/IMG/Vicente/venus.jpg", "x":0, "y":0, "coordx":354.2879943847656, "coordy":362.86399841308594, "cx":374.2879943847656, "cy":382.86399841308594, "rotation":180, "pedestalAncho":0, "pedestalAlto":0, "pathX3D": "./uploads/X3D/Vicente/venus.x3d", "pathOBJ": "./uploads/OBJ/Vicente/venus.obj"}  ], "cuadros" : [{ "nombre" : "Noche Estrellada0",  "id": "Noche Estrellada0", "nombreBD": "Noche Estrellada", "height":40, "width":40, "location": "./uploads/IMG/Vicente/nocheestrelladacanvas.png", "x":0, "y":0, "cx":194, "cy":30, "rotation":0, "largo":0.2, "alto":0.15, "textura": "./uploads/IMG/Vicente/nocheestrellada.jpg"} , { "nombre" : "Noche Estrellada1",  "id": "Noche Estrellada1", "nombreBD": "Noche Estrellada", "height":40, "width":40, "location": "./uploads/IMG/Vicente/nocheestrelladacanvas.png", "x":0, "y":0, "cx":75, "cy":185, "rotation":265, "largo":0.2, "alto":0.15, "textura": "./uploads/IMG/Vicente/nocheestrellada.jpg"} , { "nombre" : "Noche Estrellada2",  "id": "Noche Estrellada2", "nombreBD": "Noche Estrellada", "height":40, "width":40, "location": "./uploads/IMG/Vicente/nocheestrelladacanvas.png", "x":0, "y":0, "cx":351, "cy":32, "rotation":0, "largo":0.2, "alto":0.15, "textura": "./uploads/IMG/Vicente/nocheestrellada.jpg"} , { "nombre" : "Noche Estrellada3",  "id": "Noche Estrellada3", "nombreBD": "Noche Estrellada", "height":40, "width":40, "location": "./uploads/IMG/Vicente/nocheestrelladacanvas.png", "x":0, "y":0, "cx":297, "cy":164, "rotation":275, "largo":0.2, "alto":0.15, "textura": "./uploads/IMG/Vicente/nocheestrellada.jpg"} , { "nombre" : "Noche Estrellada5",  "id": "Noche Estrellada5", "nombreBD": "Noche Estrellada", "height":40, "width":40, "location": "./uploads/IMG/Vicente/nocheestrelladacanvas.png", "x":0, "y":0, "cx":245, "cy":469, "rotation":180, "largo":0.2, "alto":0.15, "textura": "./uploads/IMG/Vicente/nocheestrellada.jpg"}  ] } }